{
    "key": "81",
    "gmods": "G,1,A,Q,F,C,2,3,7,4,L,8,Z,5,M,6,9,X,U,Y",
    "col": "GS",
    "stat": "A",
    "mpkey": "1",
    "code": "AFST 951",
    "section": "02",
    "crn": "26417",
    "title": "Dir Reading & Research: Black Migrant",
    "xlist": "",
    "yc_attrs": "",
    "ci_attrs": "",
    "description": "By arrangement with faculty.",
    "hours": "",
    "regnotes": "",
    "rp_attr": "",
    "instructordetail_html": "<div class=\"instructor-detail\"><div class=\"instructor-name\"><a href=\"#\" data-action=\"search\" data-search-data-provider=\"search-by-instructor\" data-id=\"8093\">Elijah Anderson</a></div><div class=\"instructor-email\"><a href=\"mailto:elijah.anderson@yale.edu\">elijah.anderson@yale.edu</a></div></div>",
    "meeting_html": "",
    "final_exam": "",
    "resources": "<a href=\"#\" role=\"button\" class=\"btn\" id=\"course_eval_button\" data-crn=\"26417\" data-srcdb=\"201901\" disabled >COURSE EVALUATIONS</a><form name=\"orderBooks\" class=\"book-form\" method=\"post\" action=\"https://secure.bncollege.com/webapp/wcs/stores/servlet/TBListView?cm_mmc=RI-_-999-_-1-_-A\" target=\"_blank\"><input type=\"hidden\" name=\"catalogId\" value=\"10001\" /><input type=\"hidden\" name=\"storeId\" value=\"16556\" /><input type=\"hidden\" name=\"termMapping\" value=\"N\" /><input type=\"hidden\" name=\"courseXml\" value='<?xml version=\"1.0\" encoding=\"UTF-8\"?><textbookorder><courses><course dept=\"AFST\" num=\"951\" sect=\"2\" term=\"W19\" /></courses></textbookorder>'/><input type=\"submit\" value=\"BUY BOOKS\" role=\"button\" class=\"btn\" ></form>",
    "all_sections_remove_children": "<p class=\"titlesvary\">Class titles vary by section.</p><div class=\"course-sections\" role=\"grid\" aria-readonly=\"true\"><a role=\"row\" href=\"#\" class=\"course-section\" data-action=\"result-detail-remove-children\" data-group=\"code:AFST 951\" data-srcdb=\"201901\" data-key=\"crn:23093\"><div role=\"rowheader\" class=\"course-section-title\"><span class=\"header-text\">Title: </span> Directed Reading and Research</div><div role=\"gridcell\" class=\"course-section-section-no\"><span class=\"header-text\">Section no: </span> 01</div><div role=\"gridcell\" class=\"course-section-crn\"><span class=\"header-text\">CRN: </span> 23093</div><div role=\"gridcell\" class=\"course-section-mp\"><span class=\"header-text\">Meets: </span> HTBA</div><div role=\"gridcell\" class=\"course-section-instr\"><span class=\"header-text\">Instructor: </span> D. Simon</div></a><a role=\"row\" href=\"#\" class=\"course-section\" data-action=\"result-detail-remove-children\" data-group=\"code:AFST 951\" data-srcdb=\"201901\" data-key=\"crn:26417\"><div role=\"rowheader\" class=\"course-section-title\"><span class=\"header-text\">Title: </span> Dir Reading &amp; Research: Black Migrant</div><div role=\"gridcell\" class=\"course-section-section-no\"><span class=\"header-text\">Section no: </span> 02</div><div role=\"gridcell\" class=\"course-section-crn\"><span class=\"header-text\">CRN: </span> 26417</div><div role=\"gridcell\" class=\"course-section-mp\"><span class=\"header-text\">Meets: </span> HTBA</div><div role=\"gridcell\" class=\"course-section-instr\"><span class=\"header-text\">Instructor: </span> E. Anderson</div></a><a role=\"row\" href=\"#\" class=\"course-section\" data-action=\"result-detail-remove-children\" data-group=\"code:AFST 951\" data-srcdb=\"201901\" data-key=\"crn:26416\"><div role=\"rowheader\" class=\"course-section-title\"><span class=\"header-text\">Title: </span> Dir Reading &amp; Research: MA Thesis DR 2</div><div role=\"gridcell\" class=\"course-section-section-no\"><span class=\"header-text\">Section no: </span> 03</div><div role=\"gridcell\" class=\"course-section-crn\"><span class=\"header-text\">CRN: </span> 26416</div><div role=\"gridcell\" class=\"course-section-mp\"><span class=\"header-text\">Meets: </span> HTBA</div><div role=\"gridcell\" class=\"course-section-instr\"><span class=\"header-text\">Instructor: </span> O. Adesola</div></a><a role=\"row\" href=\"#\" class=\"course-section\" data-action=\"result-detail-remove-children\" data-group=\"code:AFST 951\" data-srcdb=\"201901\" data-key=\"crn:26418\"><div role=\"rowheader\" class=\"course-section-title\"><span class=\"header-text\">Title: </span> Directed Reading and Research</div><div role=\"gridcell\" class=\"course-section-section-no\"><span class=\"header-text\">Section no: </span> 04</div><div role=\"gridcell\" class=\"course-section-crn\"><span class=\"header-text\">CRN: </span> 26418</div><div role=\"gridcell\" class=\"course-section-mp\"><span class=\"header-text\">Meets: </span> HTBA</div><div role=\"gridcell\" class=\"course-section-instr\"><span class=\"header-text\">Instructor: </span> D. Magaziner</div></a></div>",
    "last_updated": "Tue Oct 22 2019 21:17:54 GMT-0500 (CDT)",
    "srcdb": "201901",
    "allInGroup": [
        {
            "key": "79",
            "code": "AFST 951",
            "title": "Directed Reading and Research",
            "crn": "23093",
            "no": "01",
            "total": "2",
            "schd": "F",
            "stat": "A",
            "isCancelled": "",
            "meets": "HTBA",
            "mpkey": "1",
            "instr": "D. Simon",
            "meetingTimes": "[]",
            "start_date": "2019-01-14",
            "end_date": "2019-05-08",
            "srcdb": "201901"
        },
        {
            "key": "80",
            "code": "AFST 951",
            "title": "Dir Reading & Research: MA Thesis DR 2",
            "crn": "26416",
            "no": "03",
            "total": "1",
            "schd": "F",
            "stat": "A",
            "isCancelled": "",
            "meets": "HTBA",
            "mpkey": "1",
            "instr": "O. Adesola",
            "meetingTimes": "[]",
            "start_date": "2019-01-14",
            "end_date": "2019-05-08",
            "srcdb": "201901"
        },
        {
            "key": "81",
            "code": "AFST 951",
            "title": "Dir Reading & Research: Black Migrant",
            "crn": "26417",
            "no": "02",
            "total": "1",
            "schd": "F",
            "stat": "A",
            "isCancelled": "",
            "meets": "HTBA",
            "mpkey": "1",
            "instr": "E. Anderson",
            "meetingTimes": "[]",
            "start_date": "2019-01-14",
            "end_date": "2019-05-08",
            "srcdb": "201901"
        },
        {
            "key": "82",
            "code": "AFST 951",
            "title": "Directed Reading and Research",
            "crn": "26418",
            "no": "04",
            "total": "2",
            "schd": "F",
            "stat": "A",
            "isCancelled": "",
            "meets": "HTBA",
            "mpkey": "1",
            "instr": "D. Magaziner",
            "meetingTimes": "[]",
            "start_date": "2019-01-14",
            "end_date": "2019-05-08",
            "srcdb": "201901"
        }
    ]
}