{
    "key": "53",
    "gmods": "Y",
    "col": "SU",
    "stat": "A",
    "mpkey": "5852",
    "code": "CGSC S152E",
    "section": "01",
    "crn": "30234",
    "title": "Moralities of Everyday Life",
    "xlist": "Same As: <a href=\"/search/?p=PSYC%20S152E\" data-action=\"result-detail\" data-group=\"code:PSYC S152E\" data-key=\"crn:30130\">PSYC S152E, section 01</a><br/>Same As: <a href=\"/search/?p=PHIL%20S152E\" data-action=\"result-detail\" data-group=\"code:PHIL S152E\" data-key=\"crn:30131\">PHIL S152E, section 01</a>",
    "yc_attrs": "This course can be applied towards the <i>Humanities and Arts</i> Yale College distributional requirement.",
    "ci_attrs": "",
    "description": "Offered Online. The modern science of moral thought and moral action explored through disciplines such as cognitive science, social and developmental psychology, neuroscience, behavioral economics, and analytic philosophy. Empathy and compassion in babies and young children; emotional reactions to family, friends, and strangers; the origins of prejudice and bigotry; sexuality, disgust, and purity; punishment, revenge, and forgiveness; the relationship between morality and religion. For college students and beyond. 1 Credit. Tuition: $3750. Technology fee: $85. Offered in both Session A: May 30 - July 1 (<a href=\"/search/?p=CRN%2030234\" data-action=\"result-detail\" data-group=\"code:CRN 30234\"  class=\"notoffered\">CRN 30234</a>) and Session B: July 4 - August 5 (<a href=\"/search/?p=CRN%2030235\" data-action=\"result-detail\" data-group=\"code:CRN 30235\"  class=\"notoffered\">CRN 30235</a>).",
    "hours": "",
    "regnotes": "",
    "rp_attr": "",
    "instructordetail_html": "<div class=\"instructor-detail\"><div class=\"instructor-name\"><a href=\"#\" data-action=\"search\" data-search-data-provider=\"search-by-instructor\" data-id=\"4638\">Paul Bloom</a></div><div class=\"instructor-email\"><a href=\"mailto:paul.bloom@yale.edu\">paul.bloom@yale.edu</a></div></div>",
    "meeting_html": "<div class=\"meet\">TTh 6pm-8pm</div>",
    "final_exam": "",
    "resources": "<a href=\"#\" role=\"button\" class=\"btn\" id=\"course_eval_button\" data-crn=\"30234\" data-srcdb=\"201602\" disabled >COURSE EVALUATIONS</a><a title=\"Opens in a new window.\" role=\"button\" class=\"btn\" href=\"https://yale.instructure.com/courses/549\" target=\"_blank\">HOMEPAGE</a><form name=\"orderBooks\" class=\"book-form\" method=\"post\" action=\"https://secure.bncollege.com/webapp/wcs/stores/servlet/TBListView?cm_mmc=RI-_-999-_-1-_-A\" target=\"_blank\"><input type=\"hidden\" name=\"catalogId\" value=\"10001\" /><input type=\"hidden\" name=\"storeId\" value=\"16556\" /><input type=\"hidden\" name=\"termMapping\" value=\"N\" /><input type=\"hidden\" name=\"courseXml\" value='<?xml version=\"1.0\" encoding=\"UTF-8\"?><textbookorder><courses><course dept=\"CGSC\" num=\"S152E\" sect=\"1\" term=\"B16\" /></courses></textbookorder>'/><input type=\"submit\" value=\"BUY BOOKS\" role=\"button\" class=\"btn\" ></form>",
    "all_sections_remove_children": "<div class=\"course-sections\" role=\"grid\" aria-readonly=\"true\"><a role=\"row\" href=\"#\" class=\"course-section\" data-action=\"result-detail-remove-children\" data-group=\"code:CGSC S152E\" data-srcdb=\"201602\" data-key=\"crn:30234\"><div role=\"rowheader\" class=\"course-section-section-no\"><span class=\"header-text\">Section no: </span> 01</div><div role=\"gridcell\" class=\"course-section-crn\"><span class=\"header-text\">CRN: </span> 30234</div><div role=\"gridcell\" class=\"course-section-mp\"><span class=\"header-text\">Meets: </span> TTh 6-8p</div><div role=\"gridcell\" class=\"course-section-instr\"><span class=\"header-text\">Instructor: </span> P. Bloom</div></a><a role=\"row\" href=\"#\" class=\"course-section\" data-action=\"result-detail-remove-children\" data-group=\"code:CGSC S152E\" data-srcdb=\"201602\" data-key=\"crn:30235\"><div role=\"rowheader\" class=\"course-section-section-no\"><span class=\"header-text\">Section no: </span> 02</div><div role=\"gridcell\" class=\"course-section-crn\"><span class=\"header-text\">CRN: </span> 30235</div><div role=\"gridcell\" class=\"course-section-mp\"><span class=\"header-text\">Meets: </span> TTh 7:30-9:30p</div><div role=\"gridcell\" class=\"course-section-instr\"><span class=\"header-text\">Instructor: </span> P. Bloom</div></a></div>",
    "last_updated": "Wed Aug 28 2019 16:19:49 GMT-0500 (CDT)",
    "srcdb": "201602",
    "allInGroup": [
        {
            "key": "53",
            "code": "CGSC S152E",
            "title": "Moralities of Everyday Life",
            "crn": "30234",
            "no": "01",
            "total": "2",
            "schd": "H",
            "stat": "A",
            "isCancelled": "",
            "meets": "TTh 6-8p",
            "mpkey": "5852",
            "instr": "P. Bloom",
            "meetingTimes": "[{\"meet_day\":\"1\",\"start_time\":\"1800\",\"end_time\":\"2000\"},{\"meet_day\":\"3\",\"start_time\":\"1800\",\"end_time\":\"2000\"}]",
            "start_date": "2016-05-30",
            "end_date": "2016-07-01",
            "srcdb": "201602"
        },
        {
            "key": "54",
            "code": "CGSC S152E",
            "title": "Moralities of Everyday Life",
            "crn": "30235",
            "no": "02",
            "total": "2",
            "schd": "H",
            "stat": "A",
            "isCancelled": "",
            "meets": "TTh 7:30-9:30p",
            "mpkey": "6732",
            "instr": "P. Bloom",
            "meetingTimes": "[{\"meet_day\":\"1\",\"start_time\":\"1930\",\"end_time\":\"2130\"},{\"meet_day\":\"3\",\"start_time\":\"1930\",\"end_time\":\"2130\"}]",
            "start_date": "2016-07-04",
            "end_date": "2016-08-05",
            "srcdb": "201602"
        }
    ]
}