{
    "key": "3842",
    "gmods": "Y,1,A,Q,F,C,V,2,3,7,4,G,K,J,W,L,8,Z,5,H,M,6,N,9,D,B,X,I,P,R,O,U,S,T,E",
    "col": "YC",
    "stat": "A",
    "mpkey": "2052",
    "code": "RLST 018",
    "section": "01",
    "crn": "11719",
    "title": "Yoga in South Asia and Beyond",
    "xlist": "Same As: <a href=\"/search/?p=SAST%20058\" data-action=\"result-detail\" data-group=\"code:SAST 058\" data-key=\"crn:11720\">SAST 058, section 01</a>",
    "yc_attrs": "This course can be applied towards the <i>Humanities and Arts</i> Yale College distributional requirement.",
    "ci_attrs": "",
    "description": "<p>The history of yoga practice and thought from the earliest textual discussions of yoga until the present day.\u00c2\u00a0Topics include the body, cosmology, cross-cultural interactions, colonialism, and orientalism.</p>\n<p class=\"prerequisites\">Enrollment limited to first-year students. Preregistration required; see under First-Year Seminar Program.</p>",
    "hours": "1",
    "regnotes": "",
    "rp_attr": "",
    "instructordetail_html": "<div class=\"instructor-detail\"><div class=\"instructor-name\"><a href=\"#\" data-action=\"search\" data-search-data-provider=\"search-by-instructor\" data-id=\"15227\">Supriya Gandhi</a></div></div>",
    "meeting_html": "<div class=\"meet\">MW 11:35am-12:50pm<span class=\"meet-room-201903\"> in <a href=\"https://map.yale.edu/place/building/COLL451?\" target=\"_blank\">CO451 B-04</a></span></div>",
    "final_exam": "Monday, December 16, 2019 at 2pm",
    "resources": "<a href=\"#\" role=\"button\" class=\"btn\" id=\"course_eval_button\" data-crn=\"11719\" data-srcdb=\"201903\" data-action=\"login,course-evals\" >COURSE EVALUATIONS</a><a title=\"Opens in a new window.\" role=\"button\" class=\"btn\" href=\"https://yale.instructure.com/courses/51188/assignments/syllabus\" target=\"_blank\">SYLLABUS</a><form name=\"orderBooks\" class=\"book-form\" method=\"post\" action=\"https://secure.bncollege.com/webapp/wcs/stores/servlet/TBListView?cm_mmc=RI-_-999-_-1-_-A\" target=\"_blank\"><input type=\"hidden\" name=\"catalogId\" value=\"10001\" /><input type=\"hidden\" name=\"storeId\" value=\"16556\" /><input type=\"hidden\" name=\"termMapping\" value=\"N\" /><input type=\"hidden\" name=\"courseXml\" value='<?xml version=\"1.0\" encoding=\"UTF-8\"?><textbookorder><courses><course dept=\"RLST\" num=\"018\" sect=\"1\" term=\"F19\" /></courses></textbookorder>'/><input type=\"submit\" value=\"BUY BOOKS\" role=\"button\" class=\"btn\" ></form>",
    "all_sections_remove_children": "<div class=\"course-sections\" role=\"grid\" aria-readonly=\"true\"><a role=\"row\" href=\"#\" class=\"course-section\" data-action=\"result-detail-remove-children\" data-group=\"code:RLST 018\" data-srcdb=\"201903\" data-key=\"crn:11719\"><div role=\"rowheader\" class=\"course-section-section-no\"><span class=\"header-text\">Section no: </span> 01</div><div role=\"gridcell\" class=\"course-section-crn\"><span class=\"header-text\">CRN: </span> 11719</div><div role=\"gridcell\" class=\"course-section-mp\"><span class=\"header-text\">Meets: </span> MW 11:35a-12:50p</div><div role=\"gridcell\" class=\"course-section-instr\"><span class=\"header-text\">Instructor: </span> S. Gandhi</div></a></div>",
    "last_updated": "Tue Oct 22 2019 21:17:54 GMT-0500 (CDT)",
    "srcdb": "201903",
    "allInGroup": [
        {
            "key": "3842",
            "code": "RLST 018",
            "title": "Yoga in South Asia and Beyond",
            "crn": "11719",
            "no": "01",
            "total": "1",
            "schd": "L",
            "stat": "A",
            "isCancelled": "",
            "meets": "MW 11:35a-12:50p",
            "mpkey": "2052",
            "instr": "S. Gandhi",
            "meetingTimes": "[{\"meet_day\":\"0\",\"start_time\":\"1135\",\"end_time\":\"1250\"},{\"meet_day\":\"2\",\"start_time\":\"1135\",\"end_time\":\"1250\"}]",
            "start_date": "2019-08-28",
            "end_date": "2019-12-18",
            "srcdb": "201903"
        }
    ]
}