{
    "key": "3852",
    "gmods": "G,1,A,Q,F,C,2,3,7,4,K,W,L,8,Z,5,H,M,6,9,D,X,I,U,Y",
    "col": "GS",
    "stat": "A",
    "mpkey": "2192",
    "code": "RLST 654",
    "section": "01",
    "crn": "12605",
    "title": "Biblical Interpretation in Early Christianity",
    "xlist": "",
    "yc_attrs": "",
    "ci_attrs": "",
    "description": "Scripture was both the primary focus of early Christians\u2019 literary attentions and the most significant resource for resolving questions of theological, ethical, or practical concern in their communities. Yet Scripture frequently did not speak with sufficient clarity and univocality; it required mediation\u2014in homily, hymn, commentary, and treatise\u2014and, in the process, interpretation and exposition. This course introduces students to a survey of ancient Christian writers\u2019 exegetical efforts from the very beginnings of Christian interpretive activity through the flowering of exegesis across the Roman and Sassanid Empires in the fourth through sixth century.",
    "hours": "",
    "regnotes": "",
    "rp_attr": "",
    "instructordetail_html": "<div class=\"instructor-detail\"><div class=\"instructor-name\"><a href=\"#\" data-action=\"search\" data-search-data-provider=\"search-by-instructor\" data-id=\"14985\">Maria Doerfler</a></div><div class=\"instructor-email\"><a href=\"mailto:maria.doerfler@yale.edu\">maria.doerfler@yale.edu</a></div></div>",
    "meeting_html": "<div class=\"meet\">M 9:25am-11:15am<span class=\"meet-room-201703\"> in <a href=\"https://map.yale.edu/place/building/COLL451?\" target=\"_blank\">CO451 B-04</a></span></div>",
    "final_exam": "",
    "resources": "<a href=\"#\" role=\"button\" class=\"btn\" id=\"course_eval_button\" data-crn=\"12605\" data-srcdb=\"201703\" data-action=\"login,course-evals\" >COURSE EVALUATIONS</a><a title=\"Opens in a new window.\" role=\"button\" class=\"btn\" href=\"https://yale.instructure.com/courses/31622/assignments/syllabus\" target=\"_blank\">SYLLABUS</a><form name=\"orderBooks\" class=\"book-form\" method=\"post\" action=\"https://secure.bncollege.com/webapp/wcs/stores/servlet/TBListView?cm_mmc=RI-_-999-_-1-_-A\" target=\"_blank\"><input type=\"hidden\" name=\"catalogId\" value=\"10001\" /><input type=\"hidden\" name=\"storeId\" value=\"16556\" /><input type=\"hidden\" name=\"termMapping\" value=\"N\" /><input type=\"hidden\" name=\"courseXml\" value='<?xml version=\"1.0\" encoding=\"UTF-8\"?><textbookorder><courses><course dept=\"RLST\" num=\"654\" sect=\"1\" term=\"F17\" /></courses></textbookorder>'/><input type=\"submit\" value=\"BUY BOOKS\" role=\"button\" class=\"btn\" ></form>",
    "all_sections_remove_children": "<div class=\"course-sections\" role=\"grid\" aria-readonly=\"true\"><a role=\"row\" href=\"#\" class=\"course-section\" data-action=\"result-detail-remove-children\" data-group=\"code:RLST 654\" data-srcdb=\"201703\" data-key=\"crn:12605\"><div role=\"rowheader\" class=\"course-section-section-no\"><span class=\"header-text\">Section no: </span> 01</div><div role=\"gridcell\" class=\"course-section-crn\"><span class=\"header-text\">CRN: </span> 12605</div><div role=\"gridcell\" class=\"course-section-mp\"><span class=\"header-text\">Meets: </span> M 9:25-11:15a</div><div role=\"gridcell\" class=\"course-section-instr\"><span class=\"header-text\">Instructor: </span> M. Doerfler</div></a></div>",
    "last_updated": "Wed Aug 28 2019 16:19:49 GMT-0500 (CDT)",
    "srcdb": "201703",
    "allInGroup": [
        {
            "key": "3852",
            "code": "RLST 654",
            "title": "Biblical Interpretation in Early Christianity",
            "crn": "12605",
            "no": "01",
            "total": "1",
            "schd": "L",
            "stat": "A",
            "isCancelled": "",
            "meets": "M 9:25-11:15a",
            "mpkey": "2192",
            "instr": "M. Doerfler",
            "meetingTimes": "[{\"meet_day\":\"0\",\"start_time\":\"925\",\"end_time\":\"1115\"}]",
            "start_date": "2017-08-30",
            "end_date": "2017-12-20",
            "srcdb": "201703"
        }
    ]
}