{
    "key": "4203",
    "gmods": "Y,1,A,Q,F,C,V,2,3,7,4,G,K,J,W,L,8,Z,5,H,M,6,N,9,D,B,X,I,P,R,O,U,S,T",
    "col": "YC",
    "stat": "C",
    "mpkey": "1",
    "code": "THST 310",
    "section": "01",
    "crn": "23076",
    "title": "Analysis through Action",
    "xlist": "Same As: <a href=\"/search/?p=RUSS%20310\" data-action=\"result-detail\" data-group=\"code:RUSS 310\" data-key=\"crn:23266\">RUSS 310, section 01</a>",
    "yc_attrs": "This course can be applied towards the <i>Humanities and Arts</i> Yale College distributional requirement.",
    "ci_attrs": "",
    "description": "<p>Study of \u201cAnalysis Through Action,\u201d\u00a0the Russian method of converting written word into onstage action. Rooted in the last experiments of Konstantin Stanislavski<em>,</em>\u00a0this methodology remains alive today in Russian avant-garde theater. With Anton Chekhov's,\u00a0<em>The Cherry Orchard</em>\u00a0as the master text, students examine and deploy two interdependent components: in-depth text analysis and focused physical/vocal improvisations. Some basic acting, directing, and/or dramaturgy assumed.</p>",
    "hours": "1",
    "regnotes": "",
    "rp_attr": "",
    "instructordetail_html": "",
    "meeting_html": "",
    "final_exam": "HTBA",
    "resources": "<a href=\"#\" role=\"button\" class=\"btn\" id=\"course_eval_button\" data-crn=\"23076\" data-srcdb=\"201801\" disabled >COURSE EVALUATIONS</a><a title=\"Opens in a new window.\" role=\"button\" class=\"btn\" href=\"https://yale.instructure.com/courses/36739/assignments/syllabus\" target=\"_blank\">SYLLABUS</a><form name=\"orderBooks\" class=\"book-form\" method=\"post\" action=\"https://secure.bncollege.com/webapp/wcs/stores/servlet/TBListView?cm_mmc=RI-_-999-_-1-_-A\" target=\"_blank\"><input type=\"hidden\" name=\"catalogId\" value=\"10001\" /><input type=\"hidden\" name=\"storeId\" value=\"16556\" /><input type=\"hidden\" name=\"termMapping\" value=\"N\" /><input type=\"hidden\" name=\"courseXml\" value='<?xml version=\"1.0\" encoding=\"UTF-8\"?><textbookorder><courses><course dept=\"THST\" num=\"310\" sect=\"1\" term=\"W18\" /></courses></textbookorder>'/><input type=\"submit\" value=\"BUY BOOKS\" role=\"button\" class=\"btn\" ></form>",
    "all_sections_remove_children": "<div class=\"course-sections\" role=\"grid\" aria-readonly=\"true\"><a role=\"row\" href=\"#\" class=\"course-section\" data-action=\"result-detail-remove-children\" data-group=\"code:THST 310\" data-srcdb=\"201801\" data-key=\"crn:23076\"><div role=\"rowheader\" class=\"course-section-section-no\"><span class=\"header-text\">Section no: </span> 01</div><div role=\"gridcell\" class=\"course-section-crn\"><span class=\"header-text\">CRN: </span> 23076</div><div role=\"gridcell\" class=\"course-section-mp\"><span class=\"header-text\">Meets: </span> HTBA</div><div role=\"gridcell\" class=\"course-section-instr\"><span class=\"header-text\">Instructor: </span> Staff</div></a></div>",
    "last_updated": "Wed Aug 28 2019 16:19:49 GMT-0500 (CDT)",
    "srcdb": "201801",
    "allInGroup": [
        {
            "key": "4203",
            "code": "THST 310",
            "title": "Analysis through Action",
            "crn": "23076",
            "no": "01",
            "total": "1",
            "schd": "N",
            "stat": "C",
            "isCancelled": "1",
            "meets": "HTBA",
            "mpkey": "1",
            "instr": "Staff",
            "meetingTimes": "[]",
            "start_date": "2018-01-16",
            "end_date": "2018-05-09",
            "srcdb": "201801"
        }
    ]
}